{
  "_comment": "MARIUS 物料标签预设词库 — 所有标签需从此池中选择。新增标签时修改此文件。",
  "button": {
    "孔型": {
      "values": [
        "二眼",
        "四眼",
        "工字",
        "四合/暗扣",
        "撞钉",
        "手缝扣",
        "脚扣",
        "辅件"
      ],
      "synonyms": {
        "4眼": "四眼",
        "四眼/二眼": "四眼",
        "2眼": "二眼",
        "两眼": "二眼",
        "暗扣": "四合/暗扣",
        "按扣": "四合/暗扣",
        "四合": "四合/暗扣",
        "工字/撞钉": "工字",
        "铆钉": "撞钉",
        "五孔": "四眼",
        "辅件/非传统扣": "辅件",
        "猪鼻": "辅件",
        "对钩": "辅件",
        "吊钟": "辅件",
        "绳扣": "辅件",
        "胸针": "辅件",
        "装饰链": "辅件"
      }
    },
    "造型": {
      "values": [
        "扁圆",
        "拱形",
        "球形",
        "脚扣",
        "异形",
        "功能辅件",
        "平面片",
        "垫扣/副扣"
      ],
      "synonyms": {
        "球形/拱形": "球形",
        "扁平面片": "平面片",
        "扁圆拱面": "拱形",
        "微拱": "拱形",
        "球面": "球形",
        "圆球": "球形",
        "球扣": "球形",
        "凹面": "扁圆",
        "镂空": "异形",
        "绳结形": "异形",
        "不规则": "异形",
        "几何": "异形",
        "杆形": "异形",
        "绳/链": "异形",
        "链扣": "异形",
        "插扣": "功能辅件",
        "D字/猪鼻": "功能辅件",
        "功能辅件": "功能辅件",
        "胶囊形": "异形",
        "圆柱": "异形",
        "球形端": "球形",
        "D字": "功能辅件",
        "中凹": "扁圆",
        "吊钟": "功能辅件",
        "绳扣": "功能辅件",
        "装饰": "异形"
      }
    },
    "光泽": {
      "values": [
        "哑光",
        "亮光",
        "金属感",
        "珠光",
        "镜面",
        "做旧"
      ],
      "synonyms": {
        "哑光/绒感": "哑光",
        "亮光/金属感": "金属感",
        "亮光/哑光": "亮光",
        "半哑光": "哑光",
        "半哑光/亮光": "亮光",
        "喷漆/特殊表面": "亮光",
        "闪光": "珠光"
      }
    },
    "边缘": {
      "values": [
        "平边",
        "有边",
        "圆边",
        "异形边",
        "无传统边"
      ],
      "synonyms": {
        "平边/无边": "平边",
        "有边/凸边": "有边",
        "凸边": "有边",
        "圈边": "有边",
        "斜边": "异形边",
        "珠边": "异形边",
        "宽边": "有边",
        "金属边": "异形边",
        "绳纹边": "异形边",
        "放射纹": "异形边",
        "太阳纹": "异形边",
        "不规则边": "异形边",
        "直角": "异形边",
        "圆角": "异形边",
        "无孔": "无传统边",
        "无传统边": "无传统边",
        "密镶": "异形边",
        "编织": "异形边",
        "多材质": "异形边",
        "褶皱肌理": "异形边",
        "D字": "异形边",
        "圆柱": "异形边",
        "扭绳": "异形边",
        "球形端": "异形边",
        "胶囊形": "异形边"
      }
    },
    "装饰元素": {
      "values": [
        "品牌刻字",
        "花纹/图案",
        "珍珠",
        "水钻",
        "锆石",
        "宝石",
        "镂空",
        "烧边",
        "浮雕",
        "天然纹理",
        "玳瑁纹",
        "金属装饰",
        "字母组合",
        "桂冠",
        "硬币纹",
        "绳结",
        "珠链"
      ],
      "synonyms": {
        "MARIUS": "品牌刻字",
        "MS": "品牌刻字",
        "LOGO": "品牌刻字",
        "金色字母浮雕": "品牌刻字",
        "中心Logo": "品牌刻字",
        "侧边刻字": "品牌刻字",
        "点状字": "品牌刻字",
        "浮雕字": "浮雕",
        "浮雕纹": "浮雕",
        "珍珠簇": "珍珠",
        "大小珠": "珍珠",
        "水晶": "水钻",
        "黑石": "宝石",
        "塔罗/特殊孔型": "花纹/图案",
        "斜纹肌理": "天然纹理",
        "仿牛角纹": "天然纹理",
        "粗花呢": "花纹/图案",
        "花朵": "花纹/图案",
        "箔纹": "花纹/图案",
        "图案": "花纹/图案",
        "头像": "花纹/图案",
        "簇状金属花": "金属装饰",
        "金色中心": "金属装饰",
        "装饰中心": "金属装饰",
        "珠片": "金属装饰",
        "扭结/绳结造型": "绳结",
        "锯齿边": "金属装饰",
        "几何切角": "金属装饰",
        "太阳纹": "花纹/图案",
        "插扣结构": "金属装饰",
        "杆形扣": "金属装饰",
        "吊球": "金属装饰",
        "满镶": "水钻",
        "熔融/有机造型": "花纹/图案",
        "点状内圈": "金属装饰"
      }
    },
    "风格": {
      "values": [
        "基础款",
        "经典",
        "优雅",
        "轻奢",
        "奢华",
        "商务",
        "小香风",
        "复古",
        "前卫",
        "功能",
        "运动休闲",
        "牛仔",
        "装饰",
        "品牌",
        "女性化",
        "英伦"
      ],
      "synonyms": {
        "基础": "基础款",
        "简约": "基础款",
        "极简": "基础款",
        "低调": "基础款",
        "实用": "基础款",
        "功能五金": "功能",
        "工业": "功能",
        "高级": "轻奢",
        "精致": "轻奢",
        "闪耀": "奢华",
        "珠宝感": "奢华",
        "高定": "奢华",
        "巴洛克": "奢华",
        "现代": "基础款",
        "运动": "运动休闲",
        "户外": "运动休闲",
        "几何": "前卫",
        "艺术": "前卫",
        "哥特": "前卫",
        "品牌识别": "品牌",
        "装饰辅件": "装饰"
      }
    },
    "适用场景": {
      "values": [
        "外套",
        "大衣",
        "衬衫",
        "西装",
        "针织",
        "开衫",
        "内搭",
        "裤装",
        "牛仔",
        "工装",
        "连衣裙",
        "礼服",
        "制服",
        "小香风套装",
        "风衣",
        "运动",
        "帽绳",
        "包袋",
        "童装",
        "通用"
      ],
      "synonyms": {
        "高定": "礼服",
        "晚装": "礼服",
        "女装": "通用",
        "副扣": "内搭",
        "装饰": "通用",
        "功能件": "工装",
        "功能": "工装",
        "休闲": "通用",
        "腰带": "裤装",
        "边饰": "内搭",
        "口袋": "裤装",
        "抽绳": "帽绳",
        "粗花呢": "小香风套装"
      }
    }
  },
  "fabric": {
    "织法组织": {
      "values": [
        "针织",
        "梭织",
        "斜纹",
        "平纹",
        "提花",
        "绒类"
      ],
      "synonyms": {
        "梭织/毛纺": "梭织",
        "梭织/平纹": "梭织",
        "梭织/提花": "梭织",
        "梭织平纹/细斜纹": "梭织",
        "梭织（提花肌理组织）": "梭织",
        "细密平纹": "平纹",
        "细密平纹/针织": "平纹",
        "细密针织/平纹": "针织",
        "细针织": "针织",
        "密实平纹/细斜纹": "平纹",
        "高密平纹": "平纹",
        "棉平布平纹": "平纹",
        "粗平纹": "平纹",
        "亚麻平纹": "平纹",
        "平纹竹节": "平纹",
        "府绸/高密平纹": "平纹",
        "府绸平纹": "平纹",
        "精纺平纹/细斜纹": "平纹",
        "平二重织": "平纹",
        "精纺斜纹": "斜纹",
        "精纺斜纹/平纹": "斜纹",
        "细斜纹": "斜纹",
        "高密度斜纹": "斜纹",
        "粗纺花呢斜纹": "斜纹",
        "花式粗花呢": "斜纹",
        "雨露麻斜纹": "斜纹",
        "提花粗织": "提花",
        "微型多臂/鸟眼纹": "提花",
        "粗花呢/圈绒": "绒类",
        "粗花呢圈圈": "绒类",
        "圈绒粗花呢": "绒类",
        "泰迪绒长毛绒": "绒类",
        "经编蕾丝": "针织",
        "树皮皱针织": "针织",
        "网布绣亮片": "针织",
        "顺纡乔其": "梭织",
        "醋酸皮感工艺": "梭织",
        "标签缎纹": "梭织",
        "不确定": "梭织",
        "其他": "梭织"
      }
    },
    "表面质感": {
      "values": [
        "哑光",
        "亮面",
        "绒感",
        "肌理感",
        "光滑"
      ],
      "synonyms": {
        "哑光/绒感": "绒感",
        "光滑/亮面": "光滑",
        "亮面/光滑": "光滑",
        "颗粒感": "肌理感",
        "哑光/肌理感": "肌理感",
        "哑光、肌理感": "肌理感",
        "哑光、微绒感": "绒感",
        "哑光平滑": "哑光",
        "哑光柔滑": "哑光",
        "哑光紧密": "哑光",
        "哑光紧致": "哑光",
        "哑光细密": "哑光",
        "哑光细粒": "哑光",
        "哑光微光泽": "哑光",
        "哑光微皱/纸感": "肌理感",
        "哑光微肌理": "肌理感",
        "哑光，带有细微绒感": "绒感",
        "平滑哑光": "光滑",
        "干爽哑光": "哑光",
        "干爽硬挺": "肌理感",
        "干爽粗糙/哑光": "肌理感",
        "颗粒哑光": "肌理感",
        "颗粒感/哑光": "肌理感",
        "颗粒感/肌理感": "肌理感",
        "肌理感、颗粒感": "肌理感",
        "肌理感、颗粒感、哑光": "肌理感",
        "肌理感/哑光与微光交织": "肌理感",
        "肌理感（哑光压纹质感）": "肌理感",
        "粗糙/干爽": "肌理感",
        "天然粗糙": "肌理感",
        "平整细腻": "光滑",
        "微光泽": "亮面",
        "金属光泽": "亮面",
        "金属闪烁": "亮面",
        "烫金微闪": "亮面",
        "珠光皱褶": "亮面",
        "凹凸亮片闪": "亮面",
        "凹凸金属闪": "亮面",
        "立体绒感/金属闪": "亮面",
        "纵向皱褶丝光": "亮面",
        "绒感哑光": "绒感",
        "绒感/丝光（苏力羊驼推断）": "绒感",
        "毛绒厚实": "绒感",
        "毛茸粗犷": "绒感",
        "蓬松毛绒": "绒感",
        "蓬松绒感": "绒感",
        "亚麻肌理柔软": "肌理感",
        "皮感微皱/哑光缎光": "肌理感",
        "立体浮雕/柔软": "肌理感",
        "细腻哑光": "哑光",
        "细腻微弹": "光滑"
      }
    },
    "花纹图案": {
      "values": [
        "纯色",
        "格纹",
        "条纹",
        "人字纹",
        "花型",
        "杂色",
        "波点",
        "品牌标识"
      ],
      "synonyms": {
        "威尔士格纹": "格纹",
        "微格/威尔士亲王格": "格纹",
        "微格纹肌理": "格纹",
        "横条格纹": "格纹",
        "格纹/杂色": "格纹",
        "细窗格纹": "格纹",
        "影条纹/细竖条": "条纹",
        "粉笔竖条": "条纹",
        "色织杂色": "杂色",
        "杂色斑点": "杂色",
        "杂色点状": "杂色",
        "杂色纯色": "杂色",
        "杂色花灰": "杂色",
        "混色肌理": "杂色",
        "纯色金银丝": "纯色",
        "树皮肌理纯色": "纯色",
        "大朵花卉印花": "花型",
        "大花卉叶片": "花型",
        "大写意植物花卉": "花型",
        "抽象涡纹": "花型",
        "其他（抽象印花）": "花型",
        "纹章标识": "品牌标识",
        "肌理花纹": "花型",
        "竖列亮片": "纯色",
        "波点": "波点"
      }
    },
    "厚薄感": {
      "values": [
        "轻薄",
        "中等",
        "厚重",
        "加厚"
      ],
      "synonyms": {
        "不确定": "中等",
        "薄": "轻薄",
        "薄款": "轻薄",
        "薄透": "轻薄",
        "极薄": "轻薄",
        "中厚": "中等",
        "中等偏厚": "中等",
        "中等偏薄": "中等"
      }
    },
    "克重档位": {
      "values": [
        "超轻(<150g)",
        "轻量(150-250g)",
        "中量(250-400g)",
        "重量(400-600g)",
        "超重(>600g)"
      ],
      "synonyms": {}
    },
    "色系": {
      "values": [
        "冷色",
        "暖色",
        "中性"
      ],
      "synonyms": {
        "其他": "中性",
        "冷色/暖色/中性/其他": "中性",
        "白色": "中性",
        "黑色": "中性",
        "大地色": "暖色",
        "红色系": "暖色",
        "紫色": "冷色",
        "多彩": "中性"
      }
    },
    "风格": {
      "values": [
        "经典",
        "商务",
        "休闲",
        "优雅",
        "轻奢",
        "自然",
        "小香风",
        "复古",
        "功能性",
        "运动休闲",
        "保暖",
        "夏日",
        "垂坠"
      ],
      "synonyms": {
        "日常": "休闲",
        "简约": "休闲",
        "通勤": "商务",
        "现代": "经典",
        "利落": "经典",
        "工装": "功能性",
        "易打理": "功能性",
        "户外": "运动休闲",
        "运动": "运动休闲"
      }
    }
  }
}